nanite_model_sneddon_spher/__init__.py
nanite_model_sneddon_spher/_version.py
nanite_model_sneddon_spher/model_sneddon_spherical.cp310-win_amd64.pyd
nanite_model_sneddon_spher/model_sneddon_spherical.pyx
nanite_model_sneddon_spher-1.0.2.dist-info/LICENSE
nanite_model_sneddon_spher-1.0.2.dist-info/METADATA
nanite_model_sneddon_spher-1.0.2.dist-info/WHEEL
nanite_model_sneddon_spher-1.0.2.dist-info/top_level.txt
nanite_model_sneddon_spher-1.0.2.dist-info/RECORD
