Metadata-Version: 2.1
Name: nanite_model_sneddon_spher
Version: 1.0.2
Summary: Sneddon model for AFM analysis in nanite
Author: Paul Müller
Maintainer-email: Paul Müller <dev@craban.de>
License: GPL version 3
Project-URL: source, https://github.com/AFM-Analysis/nanite_model_sneddon_spher
Project-URL: tracker, https://github.com/AFM-Analysis/nanite/nanite_model_sneddon_spher
Project-URL: changelog, https://github.com/AFM-analysis/nanite_model_sneddon_spher/CHANGELOG
Keywords: atomic force microscopy,mechanical phenotyping,tissue analysis
Classifier: Operating System :: OS Independent
Classifier: Programming Language :: Python :: 3
Classifier: Topic :: Scientific/Engineering :: Visualization
Classifier: Intended Audience :: Science/Research
Requires-Python: <4,>=3.10
License-File: LICENSE
Requires-Dist: lmfit >=1
Requires-Dist: numpy >=1.22.0
